dacapo_toolbox/__init__.py
dacapo_toolbox/dataset.py
dacapo_toolbox/postprocessing.py
dacapo_toolbox/py.typed
dacapo_toolbox/sample_datasets.py
dacapo_toolbox/tmp.py
dacapo_toolbox/modules/__init__.py
dacapo_toolbox/modules/distance_head.py
dacapo_toolbox/transforms/affs.py
dacapo_toolbox/transforms/distances.py
dacapo_toolbox/transforms/lsds.py
dacapo_toolbox/transforms/weight_balancing.py
dacapo_toolbox/vis/preview.py
dacapo_toolbox-1.0.0.dist-info/METADATA
dacapo_toolbox-1.0.0.dist-info/WHEEL
dacapo_toolbox-1.0.0.dist-info/top_level.txt
dacapo_toolbox-1.0.0.dist-info/RECORD
